sealy-0.3.0.dist-info/METADATA
sealy-0.3.0.dist-info/WHEEL
sealy-0.3.0.dist-info/licenses/LICENSE
sealy/sealy.pyi
sealy/__init__.py
sealy/parameters.py
sealy/py.typed
sealy/sealy.cpython-310-darwin.so
sealy-0.3.0.dist-info/RECORD
